pyqtclass/__init__.py
pyqtclass/core.py
pyqtclass-0.5.3.dist-info/LICENSE
pyqtclass-0.5.3.dist-info/METADATA
pyqtclass-0.5.3.dist-info/WHEEL
pyqtclass-0.5.3.dist-info/top_level.txt
pyqtclass-0.5.3.dist-info/RECORD
