Metadata-Version: 2.1
Name: pyqtclass
Version: 0.5.3
Summary: PyQt 기반으로 동작하는 객체들의 베이스클래스 모음 패키지
Home-page: https://github.com/innovata/PyQtClasses
Author: innovata
Author-email: iinnovata@gmail.com
Classifier: Programming Language :: Python :: 3
Classifier: License :: OSI Approved :: MIT License
Classifier: Operating System :: OS Independent
Requires-Python: >=3.8
License-File: LICENSE
Requires-Dist: PyQt5
Requires-Dist: ipylib
